netherrack/__init__.py
netherrack/netherite.py
netherrack/netherrack.py
netherrack-1.4.dist-info/LICENSE
netherrack-1.4.dist-info/METADATA
netherrack-1.4.dist-info/WHEEL
netherrack-1.4.dist-info/top_level.txt
netherrack-1.4.dist-info/RECORD
