Metadata-Version: 2.1
Name: netherrack
Version: 1.4
Summary: Netherrack is a tool to convert Python code into DF code templates.
Home-page: https://github.com/rassoolls/netherrack-docs/blob/master/README.md
Author: DFIdentity
Author-email: 
License: UNKNOWN
Platform: UNKNOWN
Classifier: Programming Language :: Python :: 3
Classifier: License :: OSI Approved :: MIT License
Classifier: Operating System :: OS Independent
Requires-Python: >=3.5
